[{
      "student_id": "pk_37567",
      "progress": [{
          "points": "0",
          "time": "0"
      }, {
          "points": "10",
          "time": "5"
      }, {
          "points": "40",
          "time": "20"
      }]
  }, {
      "student_id": "pk_63169",
      "progress": [{
          "points": "0",
          "time": "0"
      }, {
          "points": "10",
          "time": "10"
      }, {
          "points": "40",
          "time": "40"
      }]
  }, {
      "student_id": "pk_51055",
      "progress": [{
          "points": "0",
          "time": "0"
      }, {
          "points": "10",
          "time": "8"
      }, {
          "points": "30",
          "time": "25"
      }, {
          "points": "40",
          "time": "30"
      }]
  }
  ]
